datamodel_code_generator/__init__.py
datamodel_code_generator/__main__.py
datamodel_code_generator/format.py
datamodel_code_generator/http.py
datamodel_code_generator/imports.py
datamodel_code_generator/model/__init__.py
datamodel_code_generator/model/base.py
datamodel_code_generator/model/dataclass.py
datamodel_code_generator/model/enum.py
datamodel_code_generator/model/improts.py
datamodel_code_generator/model/pydantic/__init__.py
datamodel_code_generator/model/pydantic/base_model.py
datamodel_code_generator/model/pydantic/custom_root_type.py
datamodel_code_generator/model/pydantic/dataclass.py
datamodel_code_generator/model/pydantic/imports.py
datamodel_code_generator/model/pydantic/types.py
datamodel_code_generator/model/pydantic_v2/__init__.py
datamodel_code_generator/model/pydantic_v2/base_model.py
datamodel_code_generator/model/pydantic_v2/imports.py
datamodel_code_generator/model/pydantic_v2/root_model.py
datamodel_code_generator/model/pydantic_v2/types.py
datamodel_code_generator/model/rootmodel.py
datamodel_code_generator/model/template/dataclass.jinja2
datamodel_code_generator/model/template/Enum.jinja2
datamodel_code_generator/model/template/pydantic/BaseModel.jinja2
datamodel_code_generator/model/template/pydantic/BaseModel_root.jinja2
datamodel_code_generator/model/template/pydantic/Config.jinja2
datamodel_code_generator/model/template/pydantic/dataclass.jinja2
datamodel_code_generator/model/template/pydantic_v2/BaseModel.jinja2
datamodel_code_generator/model/template/pydantic_v2/ConfigDict.jinja2
datamodel_code_generator/model/template/pydantic_v2/RootModel.jinja2
datamodel_code_generator/model/template/root.jinja2
datamodel_code_generator/model/template/TypedDict.jinja2
datamodel_code_generator/model/template/TypedDictClass.jinja2
datamodel_code_generator/model/template/TypedDictFunction.jinja2
datamodel_code_generator/model/typed_dict.py
datamodel_code_generator/model/types.py
datamodel_code_generator/parser/__init__.py
datamodel_code_generator_genson_wheel-0.25.6.dist-info/entry_points.txt
datamodel_code_generator_genson_wheel-0.25.6.dist-info/LICENSE
datamodel_code_generator_genson_wheel-0.25.6.dist-info/METADATA
datamodel_code_generator_genson_wheel-0.25.6.dist-info/WHEEL
datamodel_code_generator_genson_wheel-0.25.6.dist-info/RECORD
