Metadata-Version: 2.1
Name: datamodel-code-generator-genson-wheel
Version: 0.25.6
Summary: Datamodel Code Generator
Home-page: https://github.com/koxudaxi/datamodel-code-generator
License: MIT
Author: Koudai Aono
Author-email: koxudaxi@gmail.com
Requires-Python: >=3.7,<4.0
Classifier: Development Status :: 4 - Beta
Classifier: License :: OSI Approved :: MIT License
Classifier: Natural Language :: English
Classifier: Programming Language :: Python :: 3
Classifier: Programming Language :: Python :: 3.7
Classifier: Programming Language :: Python :: 3.8
Classifier: Programming Language :: Python :: 3.9
Classifier: Programming Language :: Python :: 3.10
Classifier: Programming Language :: Python :: 3.11
Classifier: Programming Language :: Python :: 3.12
Classifier: Programming Language :: Python :: Implementation :: CPython
Provides-Extra: http
Requires-Dist: PySnooper (>=0.4.1,<2.0.0)
Requires-Dist: argcomplete (>=1.10,<4.0)
Requires-Dist: black (>=19.10b0)
Requires-Dist: genson-wheel (>=1.2.1,<2.0)
Requires-Dist: httpx ; extra == "http"
Requires-Dist: inflect (>=4.1.0,<6.0)
Requires-Dist: isort (>=4.3.21,<6.0)
Requires-Dist: jinja2 (>=2.10.1,<4.0)
Requires-Dist: openapi-spec-validator (>=0.2.8,<=0.5.2)
Requires-Dist: packaging
Requires-Dist: prance (>=0.18.2)
Requires-Dist: pydantic[email] (>=1.10.0,<3.0) ; python_version >= "3.11" and python_version < "4.0"
Requires-Dist: pydantic[email] (>=1.5.1,<3.0) ; python_version < "3.10"
Requires-Dist: pydantic[email] (>=1.9.0,<3.0) ; python_version >= "3.10" and python_version < "3.11"
Requires-Dist: toml (>=0.10.0,<1.0.0)
Project-URL: Repository, https://github.com/koxudaxi/datamodel-code-generator
